LICENCE.txt
MANIFEST.in
PYPI.md
README.md
pyproject.toml
requirements-build.txt
requirements.txt
setup.py
cfdoc/VERSION
cfdoc/__init__.py
cfdoc/version.py
cfdoc.egg-info/PKG-INFO
cfdoc.egg-info/SOURCES.txt
cfdoc.egg-info/dependency_links.txt
cfdoc.egg-info/entry_points.txt
cfdoc.egg-info/requires.txt
cfdoc.egg-info/top_level.txt
cfdoc/cli/__init__.py
cfdoc/cli/cfdoc.py
cfdoc/lib/__init__.py
cfdoc/lib/argparse.py
cfdoc/lib/jinja2.py
cfdoc/lib/logging.py
cfdoc/lib/misc.py
cfdoc/man/cfdoc.1
cfdoc/man/cfdoc.md
cfdoc/plugins/__common__.py
cfdoc/plugins/__init__.py
cfdoc/plugins/autogroup.py
cfdoc/plugins/awsdoc.py
cfdoc/plugins/resdesc.py
cfdoc/plugins/resjson.py
cfdoc/templates/html.jinja2
cfdoc/templates/md.jinja2
cfdoc/templates/mdbb.jinja2
cfdoc/templates/mdpd.jinja2