Metadata-Version: 2.4
Name: cfdoc
Version: 2.1.0
Summary: Extract documentation from an AWS CloudFormation Template
Home-page: https://bitbucket.org/murrayandrews/cfdoc/src/master/
Author: Murray Andrews
License: 3-Clause BSD License
Platform: macOS
Platform: Linux
Classifier: Development Status :: 5 - Production/Stable
Classifier: Environment :: Console
Classifier: Intended Audience :: Developers
Classifier: Intended Audience :: System Administrators
Classifier: License :: OSI Approved :: BSD License
Classifier: Natural Language :: English
Classifier: Operating System :: MacOS
Classifier: Operating System :: POSIX :: Linux
Classifier: Programming Language :: Python :: 3 :: Only
Classifier: Topic :: Utilities
Requires-Python: >=3.9.0
License-File: LICENCE.txt
Requires-Dist: jinja2
Requires-Dist: beautifulsoup4
Requires-Dist: pyyaml
Requires-Dist: colorama
Dynamic: author
Dynamic: classifier
Dynamic: description
Dynamic: description-content-type
Dynamic: home-page
Dynamic: license
Dynamic: license-file
Dynamic: platform
Dynamic: requires-dist
Dynamic: requires-python
Dynamic: summary
